{"bills":[{"date_due":"2017-12-13","name":"Conta de telefone","value":56.87,"done":false,"id":52321},{"date_due":"2017-12-27","name":"Condomu00ednio","value":"350","done":false,"id":8003},{"date_due":"2017-12-29","name":"Conta de luz","value":1.2,"done":false,"id":1191},{"date_due":"2017-12-12","name":"Conta de \u00e1gua","value":45.36,"done":false,"id":62522},{"date_due":"2017-12-13","name":"Condom\u00ednio","value":2300,"done":false,"id":18208},{"date_due":"2017-12-12","name":"Conta de luz","value":100,"done":false,"id":96893}]}